Workbook

Sheet Сводка
A1: СВОДКА ЗА 2026 ГОД
A3: Месяц | B3: Аудит | C3: Аренда офиса | D3: Бензин | E3: Телефонная связь | F3: Расходники | G3: Прочее | H3: Доход | I3: Расход | J3: Прибыль
A4: Январь | B4: ='Январь'!B56 | C4: ='Январь'!B57 | D4: ='Январь'!B58 | E4: ='Январь'!B59 | F4: ='Январь'!B60 | G4: ='Январь'!B61 | H4: ='Январь'!C20 | I4: ='Январь'!D54 | J4: =H4-I4
A5: Февраль | B5: ='Февраль'!B56 | C5: ='Февраль'!B57 | D5: ='Февраль'!B58 | E5: ='Февраль'!B59 | F5: ='Февраль'!B60 | G5: ='Февраль'!B61 | H5: ='Февраль'!C20 | I5: ='Февраль'!D54 | J5: =H5-I5
A6: Март | B6: ='Март'!B56 | C6: ='Март'!B57 | D6: ='Март'!B58 | E6: ='Март'!B59 | F6: ='Март'!B60 | G6: ='Март'!B61 | H6: ='Март'!C20 | I6: ='Март'!D54 | J6: =H6-I6
A7: Апрель | B7: ='Апрель'!B56 | C7: ='Апрель'!B57 | D7: ='Апрель'!B58 | E7: ='Апрель'!B59 | F7: ='Апрель'!B60 | G7: ='Апрель'!B61 | H7: ='Апрель'!C20 | I7: ='Апрель'!D54 | J7: =H7-I7
A8: Май | B8: ='Май'!B56 | C8: ='Май'!B57 | D8: ='Май'!B58 | E8: ='Май'!B59 | F8: ='Май'!B60 | G8: ='Май'!B61 | H8: ='Май'!C20 | I8: ='Май'!D54 | J8: =H8-I8
A9: Июнь | B9: ='Июнь'!B56 | C9: ='Июнь'!B57 | D9: ='Июнь'!B58 | E9: ='Июнь'!B59 | F9: ='Июнь'!B60 | G9: ='Июнь'!B61 | H9: ='Июнь'!C20 | I9: ='Июнь'!D54 | J9: =H9-I9
A10: Июль | B10: ='Июль'!B56 | C10: ='Июль'!B57 | D10: ='Июль'!B58 | E10: ='Июль'!B59 | F10: ='Июль'!B60 | G10: ='Июль'!B61 | H10: ='Июль'!C20 | I10: ='Июль'!D54 | J10: =H10-I10
A11: Август | B11: ='Август'!B56 | C11: ='Август'!B57 | D11: ='Август'!B58 | E11: ='Август'!B59 | F11: ='Август'!B60 | G11: ='Август'!B61 | H11: ='Август'!C20 | I11: ='Август'!D54 | J11: =H11-I11
A12: Сентябрь | B12: ='Сентябрь'!B56 | C12: ='Сентябрь'!B57 | D12: ='Сентябрь'!B58 | E12: ='Сентябрь'!B59 | F12: ='Сентябрь'!B60 | G12: ='Сентябрь'!B61 | H12: ='Сентябрь'!C20 | I12: ='Сентябрь'!D54 | J12: =H12-I12
A13: Октябрь | B13: ='Октябрь'!B56 | C13: ='Октябрь'!B57 | D13: ='Октябрь'!B58 | E13: ='Октябрь'!B59 | F13: ='Октябрь'!B60 | G13: ='Октябрь'!B61 | H13: ='Октябрь'!C20 | I13: ='Октябрь'!D54 | J13: =H13-I13
A14: Ноябрь | B14: ='Ноябрь'!B56 | C14: ='Ноябрь'!B57 | D14: ='Ноябрь'!B58 | E14: ='Ноябрь'!B59 | F14: ='Ноябрь'!B60 | G14: ='Ноябрь'!B61 | H14: ='Ноябрь'!C20 | I14: ='Ноябрь'!D54 | J14: =H14-I14
A15: Декабрь | B15: ='Декабрь'!B56 | C15: ='Декабрь'!B57 | D15: ='Декабрь'!B58 | E15: ='Декабрь'!B59 | F15: ='Декабрь'!B60 | G15: ='Декабрь'!B61 | H15: ='Декабрь'!C20 | I15: ='Декабрь'!D54 | J15: =H15-I15
A16: ИТОГО ЗА ГОД | B16: =SUM(B4:B15) | C16: =SUM(C4:C15) | D16: =SUM(D4:D15) | E16: =SUM(E4:E15) | F16: =SUM(F4:F15) | G16: =SUM(G4:G15) | H16: =SUM(H4:H15) | I16: =SUM(I4:I15) | J16: =SUM(J4:J15)

Sheet Январь
A1: ДОХОДЫ И РАСХОДЫ — Январь 2026
A2: Жёлтые ячейки — сюда вносить данные (дата, источник/категория, сумма). Остальное считается само (не трогать).
A3: ДОХОДЫ
A4: Дата | B4: Источник (объект) | C4: Сумма
A5: 15.01 | B5: Объект №1 (пример — сотрите) | C5: 250000
A20: ИТОГО ДОХОДЫ | C20: =SUM(C5:C19)
A22: РАСХОДЫ
A23: Дата | B23: Категория | C23: Описание | D23: Сумма
A24: 05.01 | B24: Аренда офиса | C24: Аренда за январь (пример — сотрите) | D24: 60000
A25: 10.01 | B25: Бензин | C25: Заправка служебной машины (пример — сотрите) | D25: 8000
A26: 20.01 | B26: Аудит | C26: Ежемесячный аудит (пример — сотрите) | D26: 15000
A54: ИТОГО РАСХОДЫ | D54: =SUM(D24:D53)
A55: РАСХОДЫ ПО КАТЕГОРИЯМ
A56: Аудит | B56: =SUMIF(B24:B53,A56,D24:D53)
A57: Аренда офиса | B57: =SUMIF(B24:B53,A57,D24:D53)
A58: Бензин | B58: =SUMIF(B24:B53,A58,D24:D53)
A59: Телефонная связь | B59: =SUMIF(B24:B53,A59,D24:D53)
A60: Расходники | B60: =SUMIF(B24:B53,A60,D24:D53)
A61: Прочее | B61: =SUMIF(B24:B53,A61,D24:D53)
A64: ИТОГ ЗА МЕСЯЦ
A65: Доходы | B65: =C20
A66: Расходы | B66: =D54
A67: Прибыль / убыток | B67: =B65-B66

Sheet Февраль
A1: ДОХОДЫ И РАСХОДЫ — Февраль 2026
A2: Жёлтые ячейки — сюда вносить данные (дата, источник/категория, сумма). Остальное считается само (не трогать).
A3: ДОХОДЫ
A4: Дата | B4: Источник (объект) | C4: Сумма
A20: ИТОГО ДОХОДЫ | C20: =SUM(C5:C19)
A22: РАСХОДЫ
A23: Дата | B23: Категория | C23: Описание | D23: Сумма
A54: ИТОГО РАСХОДЫ | D54: =SUM(D24:D53)
A55: РАСХОДЫ ПО КАТЕГОРИЯМ
A56: Аудит | B56: =SUMIF(B24:B53,A56,D24:D53)
A57: Аренда офиса | B57: =SUMIF(B24:B53,A57,D24:D53)
A58: Бензин | B58: =SUMIF(B24:B53,A58,D24:D53)
A59: Телефонная связь | B59: =SUMIF(B24:B53,A59,D24:D53)
A60: Расходники | B60: =SUMIF(B24:B53,A60,D24:D53)
A61: Прочее | B61: =SUMIF(B24:B53,A61,D24:D53)
A64: ИТОГ ЗА МЕСЯЦ
A65: Доходы | B65: =C20
A66: Расходы | B66: =D54
A67: Прибыль / убыток | B67: =B65-B66

Sheet Март
A1: ДОХОДЫ И РАСХОДЫ — Март 2026
A2: Жёлтые ячейки — сюда вносить данные (дата, источник/категория, сумма). Остальное считается само (не трогать).
A3: ДОХОДЫ
A4: Дата | B4: Источник (объект) | C4: Сумма
A20: ИТОГО ДОХОДЫ | C20: =SUM(C5:C19)
A22: РАСХОДЫ
A23: Дата | B23: Категория | C23: Описание | D23: Сумма
A54: ИТОГО РАСХОДЫ | D54: =SUM(D24:D53)
A55: РАСХОДЫ ПО КАТЕГОРИЯМ
A56: Аудит | B56: =SUMIF(B24:B53,A56,D24:D53)
A57: Аренда офиса | B57: =SUMIF(B24:B53,A57,D24:D53)
A58: Бензин | B58: =SUMIF(B24:B53,A58,D24:D53)
A59: Телефонная связь | B59: =SUMIF(B24:B53,A59,D24:D53)
A60: Расходники | B60: =SUMIF(B24:B53,A60,D24:D53)
A61: Прочее | B61: =SUMIF(B24:B53,A61,D24:D53)
A64: ИТОГ ЗА МЕСЯЦ
A65: Доходы | B65: =C20
A66: Расходы | B66: =D54
A67: Прибыль / убыток | B67: =B65-B66

Sheet Апрель
A1: ДОХОДЫ И РАСХОДЫ — Апрель 2026
A2: Жёлтые ячейки — сюда вносить данные (дата, источник/категория, сумма). Остальное считается само (не трогать).
A3: ДОХОДЫ
A4: Дата | B4: Источник (объект) | C4: Сумма
A20: ИТОГО ДОХОДЫ | C20: =SUM(C5:C19)
A22: РАСХОДЫ
A23: Дата | B23: Категория | C23: Описание | D23: Сумма
A54: ИТОГО РАСХОДЫ | D54: =SUM(D24:D53)
A55: РАСХОДЫ ПО КАТЕГОРИЯМ
A56: Аудит | B56: =SUMIF(B24:B53,A56,D24:D53)
A57: Аренда офиса | B57: =SUMIF(B24:B53,A57,D24:D53)
A58: Бензин | B58: =SUMIF(B24:B53,A58,D24:D53)
A59: Телефонная связь | B59: =SUMIF(B24:B53,A59,D24:D53)
A60: Расходники | B60: =SUMIF(B24:B53,A60,D24:D53)
A61: Прочее | B61: =SUMIF(B24:B53,A61,D24:D53)
A64: ИТОГ ЗА МЕСЯЦ
A65: Доходы | B65: =C20
A66: Расходы | B66: =D54
A67: Прибыль / убыток | B67: =B65-B66

Sheet Май
A1: ДОХОДЫ И РАСХОДЫ — Май 2026
A2: Жёлтые ячейки — сюда вносить данные (дата, источник/категория, сумма). Остальное считается само (не трогать).
A3: ДОХОДЫ
A4: Дата | B4: Источник (объект) | C4: Сумма
A20: ИТОГО ДОХОДЫ | C20: =SUM(C5:C19)
A22: РАСХОДЫ
A23: Дата | B23: Категория | C23: Описание | D23: Сумма
A54: ИТОГО РАСХОДЫ | D54: =SUM(D24:D53)
A55: РАСХОДЫ ПО КАТЕГОРИЯМ
A56: Аудит | B56: =SUMIF(B24:B53,A56,D24:D53)
A57: Аренда офиса | B57: =SUMIF(B24:B53,A57,D24:D53)
A58: Бензин | B58: =SUMIF(B24:B53,A58,D24:D53)
A59: Телефонная связь | B59: =SUMIF(B24:B53,A59,D24:D53)
A60: Расходники | B60: =SUMIF(B24:B53,A60,D24:D53)
A61: Прочее | B61: =SUMIF(B24:B53,A61,D24:D53)
A64: ИТОГ ЗА МЕСЯЦ
A65: Доходы | B65: =C20
A66: Расходы | B66: =D54
A67: Прибыль / убыток | B67: =B65-B66

Sheet Июнь
A1: ДОХОДЫ И РАСХОДЫ — Июнь 2026
A2: Жёлтые ячейки — сюда вносить данные (дата, источник/категория, сумма). Остальное считается само (не трогать).
A3: ДОХОДЫ
A4: Дата | B4: Источник (объект) | C4: Сумма
A20: ИТОГО ДОХОДЫ | C20: =SUM(C5:C19)
A22: РАСХОДЫ
A23: Дата | B23: Категория | C23: Описание | D23: Сумма
A54: ИТОГО РАСХОДЫ | D54: =SUM(D24:D53)
A55: РАСХОДЫ ПО КАТЕГОРИЯМ
A56: Аудит | B56: =SUMIF(B24:B53,A56,D24:D53)
A57: Аренда офиса | B57: =SUMIF(B24:B53,A57,D24:D53)
A58: Бензин | B58: =SUMIF(B24:B53,A58,D24:D53)
A59: Телефонная связь | B59: =SUMIF(B24:B53,A59,D24:D53)
A60: Расходники | B60: =SUMIF(B24:B53,A60,D24:D53)
A61: Прочее | B61: =SUMIF(B24:B53,A61,D24:D53)
A64: ИТОГ ЗА МЕСЯЦ
A65: Доходы | B65: =C20
A66: Расходы | B66: =D54
A67: Прибыль / убыток | B67: =B65-B66

Sheet Июль
A1: ДОХОДЫ И РАСХОДЫ — Июль 2026
A2: Жёлтые ячейки — сюда вносить данные (дата, источник/категория, сумма). Остальное считается само (не трогать).
A3: ДОХОДЫ
A4: Дата | B4: Источник (объект) | C4: Сумма
A20: ИТОГО ДОХОДЫ | C20: =SUM(C5:C19)
A22: РАСХОДЫ
A23: Дата | B23: Категория | C23: Описание | D23: Сумма
A54: ИТОГО РАСХОДЫ | D54: =SUM(D24:D53)
A55: РАСХОДЫ ПО КАТЕГОРИЯМ
A56: Аудит | B56: =SUMIF(B24:B53,A56,D24:D53)
A57: Аренда офиса | B57: =SUMIF(B24:B53,A57,D24:D53)
A58: Бензин | B58: =SUMIF(B24:B53,A58,D24:D53)
A59: Телефонная связь | B59: =SUMIF(B24:B53,A59,D24:D53)
A60: Расходники | B60: =SUMIF(B24:B53,A60,D24:D53)
A61: Прочее | B61: =SUMIF(B24:B53,A61,D24:D53)
A64: ИТОГ ЗА МЕСЯЦ
A65: Доходы | B65: =C20
A66: Расходы | B66: =D54
A67: Прибыль / убыток | B67: =B65-B66

Sheet Август
A1: ДОХОДЫ И РАСХОДЫ — Август 2026
A2: Жёлтые ячейки — сюда вносить данные (дата, источник/категория, сумма). Остальное считается само (не трогать).
A3: ДОХОДЫ
A4: Дата | B4: Источник (объект) | C4: Сумма
A20: ИТОГО ДОХОДЫ | C20: =SUM(C5:C19)
A22: РАСХОДЫ
A23: Дата | B23: Категория | C23: Описание | D23: Сумма
A54: ИТОГО РАСХОДЫ | D54: =SUM(D24:D53)
A55: РАСХОДЫ ПО КАТЕГОРИЯМ
A56: Аудит | B56: =SUMIF(B24:B53,A56,D24:D53)
A57: Аренда офиса | B57: =SUMIF(B24:B53,A57,D24:D53)
A58: Бензин | B58: =SUMIF(B24:B53,A58,D24:D53)
A59: Телефонная связь | B59: =SUMIF(B24:B53,A59,D24:D53)
A60: Расходники | B60: =SUMIF(B24:B53,A60,D24:D53)
A61: Прочее | B61: =SUMIF(B24:B53,A61,D24:D53)
A64: ИТОГ ЗА МЕСЯЦ
A65: Доходы | B65: =C20
A66: Расходы | B66: =D54
A67: Прибыль / убыток | B67: =B65-B66

Sheet Сентябрь
A1: ДОХОДЫ И РАСХОДЫ — Сентябрь 2026
A2: Жёлтые ячейки — сюда вносить данные (дата, источник/категория, сумма). Остальное считается само (не трогать).
A3: ДОХОДЫ
A4: Дата | B4: Источник (объект) | C4: Сумма
A20: ИТОГО ДОХОДЫ | C20: =SUM(C5:C19)
A22: РАСХОДЫ
A23: Дата | B23: Категория | C23: Описание | D23: Сумма
A54: ИТОГО РАСХОДЫ | D54: =SUM(D24:D53)
A55: РАСХОДЫ ПО КАТЕГОРИЯМ
A56: Аудит | B56: =SUMIF(B24:B53,A56,D24:D53)
A57: Аренда офиса | B57: =SUMIF(B24:B53,A57,D24:D53)
A58: Бензин | B58: =SUMIF(B24:B53,A58,D24:D53)
A59: Телефонная связь | B59: =SUMIF(B24:B53,A59,D24:D53)
A60: Расходники | B60: =SUMIF(B24:B53,A60,D24:D53)
A61: Прочее | B61: =SUMIF(B24:B53,A61,D24:D53)
A64: ИТОГ ЗА МЕСЯЦ
A65: Доходы | B65: =C20
A66: Расходы | B66: =D54
A67: Прибыль / убыток | B67: =B65-B66

Sheet Октябрь
A1: ДОХОДЫ И РАСХОДЫ — Октябрь 2026
A2: Жёлтые ячейки — сюда вносить данные (дата, источник/категория, сумма). Остальное считается само (не трогать).
A3: ДОХОДЫ
A4: Дата | B4: Источник (объект) | C4: Сумма
A20: ИТОГО ДОХОДЫ | C20: =SUM(C5:C19)
A22: РАСХОДЫ
A23: Дата | B23: Категория | C23: Описание | D23: Сумма
A54: ИТОГО РАСХОДЫ | D54: =SUM(D24:D53)
A55: РАСХОДЫ ПО КАТЕГОРИЯМ
A56: Аудит | B56: =SUMIF(B24:B53,A56,D24:D53)
A57: Аренда офиса | B57: =SUMIF(B24:B53,A57,D24:D53)
A58: Бензин | B58: =SUMIF(B24:B53,A58,D24:D53)
A59: Телефонная связь | B59: =SUMIF(B24:B53,A59,D24:D53)
A60: Расходники | B60: =SUMIF(B24:B53,A60,D24:D53)
A61: Прочее | B61: =SUMIF(B24:B53,A61,D24:D53)
A64: ИТОГ ЗА МЕСЯЦ
A65: Доходы | B65: =C20
A66: Расходы | B66: =D54
A67: Прибыль / убыток | B67: =B65-B66

Sheet Ноябрь
A1: ДОХОДЫ И РАСХОДЫ — Ноябрь 2026
A2: Жёлтые ячейки — сюда вносить данные (дата, источник/категория, сумма). Остальное считается само (не трогать).
A3: ДОХОДЫ
A4: Дата | B4: Источник (объект) | C4: Сумма
A20: ИТОГО ДОХОДЫ | C20: =SUM(C5:C19)
A22: РАСХОДЫ
A23: Дата | B23: Категория | C23: Описание | D23: Сумма
A54: ИТОГО РАСХОДЫ | D54: =SUM(D24:D53)
A55: РАСХОДЫ ПО КАТЕГОРИЯМ
A56: Аудит | B56: =SUMIF(B24:B53,A56,D24:D53)
A57: Аренда офиса | B57: =SUMIF(B24:B53,A57,D24:D53)
A58: Бензин | B58: =SUMIF(B24:B53,A58,D24:D53)
A59: Телефонная связь | B59: =SUMIF(B24:B53,A59,D24:D53)
A60: Расходники | B60: =SUMIF(B24:B53,A60,D24:D53)
A61: Прочее | B61: =SUMIF(B24:B53,A61,D24:D53)
A64: ИТОГ ЗА МЕСЯЦ
A65: Доходы | B65: =C20
A66: Расходы | B66: =D54
A67: Прибыль / убыток | B67: =B65-B66

Sheet Декабрь
A1: ДОХОДЫ И РАСХОДЫ — Декабрь 2026
A2: Жёлтые ячейки — сюда вносить данные (дата, источник/категория, сумма). Остальное считается само (не трогать).
A3: ДОХОДЫ
A4: Дата | B4: Источник (объект) | C4: Сумма
A20: ИТОГО ДОХОДЫ | C20: =SUM(C5:C19)
A22: РАСХОДЫ
A23: Дата | B23: Категория | C23: Описание | D23: Сумма
A54: ИТОГО РАСХОДЫ | D54: =SUM(D24:D53)
A55: РАСХОДЫ ПО КАТЕГОРИЯМ
A56: Аудит | B56: =SUMIF(B24:B53,A56,D24:D53)
A57: Аренда офиса | B57: =SUMIF(B24:B53,A57,D24:D53)
A58: Бензин | B58: =SUMIF(B24:B53,A58,D24:D53)
A59: Телефонная связь | B59: =SUMIF(B24:B53,A59,D24:D53)
A60: Расходники | B60: =SUMIF(B24:B53,A60,D24:D53)
A61: Прочее | B61: =SUMIF(B24:B53,A61,D24:D53)
A64: ИТОГ ЗА МЕСЯЦ
A65: Доходы | B65: =C20
A66: Расходы | B66: =D54
A67: Прибыль / убыток | B67: =B65-B66
